[
   {
      "id": "120363042711587666@g.us",
      "key": "CARI AKUN FF",
      "response": "Need akun ff 50-90 ada mc",
      "isImage": false,
      "image_url": "-"
   },
   {
      "id": "120363042711587666@g.us",
      "key": "JUAL UNCHECK FRESH",
      "response": "💶*JUAL UNCHEK  FRESH📌*\n\n      *BY  ROY  STORE \n\n*Di Jamin Aman & Amanah*\n\n*YG MAU ORDER SILAHKAN PC!*\n\nSEDIA UNCHEK FF FRESH DAN NEW\n💶LIST HARGA UNCHEK GG💶\n\n*💰15 UNCHEK = 10K💵20%GG*\n*💰20 UNCHEK = 15K💵 40%GG*\n*💰25 UNCHEK = 20K💵 60%GG*\n*💰30 UNCHEK = 25K💵 80%GG*\n*💰40 UNCHEK = 30K💵100%GG*\n💷LIST HARGA UNCHEK OLD💷\n\n*📛20 UNCHEK = 15K💵  20%OLD*\n*📛25 UNCHEK = 20K💵  40%OLD*\n*📛30 UNCHEK = 25K💵  60%OLD*\n*📛40 UNCHEK = 30K💵  80%OLD*\n*📛65 UNCHEK = 50K💵  100%OLD*\n\n💸LIST HARGA UNCHEK PREMIUM (OLD+SULTAN)💸\n*🛡20 UNCHEK = 20K  25%OLD+SULTAN*\n*🛡30 UNCHEK = 30K  50%OLD + SULTAN*\n*🛡40 UNCHEK = 40K  75%OLD + SULTAN*\n*🛡55 UNCHEK = 50k 100%OLD +   SULTAN*\n\n*Kenapa unchek Premium lebih mahal karena terjamin akun old + sultan*\n___________________________________\n*🔥PASTIKAN ANDA SUDAH MENGETAHUI APA ITU UNCHEK SEBELUM MEMBELI🔥*\n\n*🔥UNCHEK ADALAH AKUN HASIL PHISING YANG BELUM DI CEK SAMA SEKALI, JADI KALO GAK DAPAT JANGAN SALAH KAN PENJUAL KALO ANDA DAPAT AKUN GG ATAU SULTAN BERARTI KAMU HOKI🔥*\n___________________________________\n*🔥LINK PHISING NYA INI BARU DI JAMIN DAPAT AKUN GG ATAU PUN SULTAN🔥*\n___________________________________\n*📝NOTE : JIKA KAMU BELI MINIMAL 30K TRUS TIDAK DAPAT ATAU ZONK NANTI DI GANTI DENGAN AKUN*\n___________________________________\n🔥TESTI?ADA🔥\n🔥AMAN?100%🔥\n🔥AMANAH?100%🔥\n🔥RAGU?SKIP🔥\n___________________________________\n💳PEMBAYARAN\nDANA\nPULSA INDOSAT\nOVO\nGO-PAY\n___________________________________\nhttps://wa.me/6285609882066?text=MIN+MAU+ORDER+UNCHEK",
      "isImage": false,
      "image_url": "-"
   },
   {
      "id": "120363042711587666@g.us",
      "key": "DIAMOND MOBILE LEGENDS SEMI",
      "response": "_*Diamond Mobile Legends SEMI*_\n*VIA ID + SERVER*\n\n \n\n65 Diamonds Rp 15.750\n129 Diamonds Rp. 30.550\n194 Diamonds Rp. 45.750\n530 Diamonds Rp. 119.450\n1647 Diamonds Rp. 354.780\n2767 Diamonds Rp. 580.300\n4150 Diamonds Rp. 873.140\n6966 Diamonds Rp. 1.455.000\n\n*Jika Tidak Ada Denom Yang Diinginkan Bisa Ditambahkan. Contoh 530 + 129*\n\nJam Operasional : Buka 09.00 - 19.00 WIB (LEWAT JAM DIPROSES BESOK!)\nEstimasi proses : 1 - 180 Menit\nNB : Proses maksimal 24 jam (Apabila Sistem Error/Maintenance/Overload)\n*HARGA SEWAKTU WAKTU BERUBAH*\n\nhttp://wa.me/6288223835987?text=MASS+MAU+LINK+GRUPNYA",
      "isImage": false,
      "image_url": "-"
   },
   {
      "id": "120363042711587666@g.us",
      "key": "CARI AKUN FF NGAB",
      "response": "BUAT BUYER ADA MC",
      "isImage": false,
      "image_url": "-"
   },
   {
      "id": "120363042711587666@g.us",
      "key": "JASA UPGRADE ALL PAYMENT",
      "response": "*♻️JASA UPGRADE ALL PAYMENT BY ASES STORE♻️* \n\n*🔴UPGRADE GOPAY*\n*🔴UPGRADE DANA*\n*🔴UPGRADE OVO*\n*🔴UPGRADE LINKAJA*\n*🔴UPGRADE DANA BISNIS*\n*🔴UPGRADE SHOPEE PAY*\n*🔴UPGRADE QRIS TOPINDO*\n\n*📠PAYMENTKU*\n*💶GOPAY*\n*💶DANA*\n*💶OVO*\n*💶QRIS ALL PAYMENT*\n*💶PULSA*\n\n*📲MINAT CP MEE*\nhttp://wa.me/6289684581127?text=BG+SAYA+MAU+ORDER+JASA+UPGRADE",
      "isImage": false,
      "image_url": "-"
   },
   {
      "id": "120363041567830603@g.us",
      "key": "TOP UP DIAMOND FREE FIRE VIA ID",
      "response": "*TOP UP DIAMOND FREE FIRE VIA ID*\n\nBY:BOICHI STORE\n\n💎50DM : 7.000\n💎70DM : 10.000\n💎100DM : 14.500\n💎140DM : 19.000\n💎210DM : 28.000\n💎355DM : 47.500\n💎425DM : 57.000\n💎545DM : 73.500\n💎720DM : 93.500\n\nMEMBER MINGGU AN:\n29.000\nMEMBER BULANAN:\n145.000\n\n*PROSES 1-5 MENIT PALING LAMA 6JAM MAX, JIKA MAINTENANCE*\n\nLEGAL 100%√\nVIA ID√",
      "isImage": false,
      "image_url": "-"
   },
   {
      "id": "120363041567830603@g.us",
      "key": "DIAMOND MLBB FAST",
      "response": "_*MLBB FAST*_\nVia Id + Server (Proses 60-180 Menit, Maks 24 Jam)\n͏͏͏͏͏͏͏͏͏͏͏͏͏͏͏͏͏͏͏͏͏͏͏͏͏͏͏͏͏͏͏͏͏͏͏͏͏͏͏͏͏͏͏͏͏͏͏͏͏͏͏͏͏͏͏͏͏͏͏͏͏͏͏͏͏͏͏͏͏͏͏͏͏͏͏͏͏͏͏͏͏͏͏͏͏͏͏͏͏͏͏͏͏͏͏͏͏͏͏͏͏͏͏͏͏͏͏͏͏͏͏͏͏͏͏͏͏͏͏͏͏͏͏͏͏͏͏͏͏͏͏͏͏͏͏͏͏͏͏͏͏͏͏͏͏͏͏͏͏͏͏͏͏͏͏͏͏͏͏͏͏͏͏͏͏͏͏͏͏͏͏͏͏͏͏͏͏͏͏͏͏͏͏͏͏͏͏͏͏͏͏͏͏͏͏͏͏͏͏͏͏͏͏͏͏͏͏͏͏͏͏͏͏͏͏͏͏͏͏͏͏͏͏͏͏͏͏͏͏͏͏͏͏͏͏͏͏͏͏͏͏͏͏͏͏͏͏͏͏͏͏͏͏͏͏͏͏͏͏͏͏͏͏͏͏͏͏͏͏͏͏͏͏͏͏͏͏͏͏͏͏͏͏͏͏͏͏͏͏͏͏͏͏͏͏͏͏͏͏͏͏͏͏͏͏͏͏͏͏͏͏͏͏͏͏͏͏͏͏͏͏͏͏͏͏͏͏͏͏͏͏͏͏͏͏͏͏͏͏͏͏͏͏͏͏͏͏͏͏͏͏͏͏͏͏͏͏͏͏͏͏͏͏͏͏͏͏͏͏͏͏͏͏͏͏͏͏͏͏͏͏͏͏͏͏͏͏͏͏͏͏͏͏͏͏͏͏͏͏͏͏͏͏͏͏͏͏͏͏͏͏͏͏͏͏͏͏͏͏͏͏͏͏͏͏͏͏͏͏͏͏͏͏͏͏͏͏͏͏͏͏͏͏͏͏͏͏͏͏͏͏͏͏͏͏͏͏͏͏͏͏͏͏͏͏͏͏͏͏͏͏͏͏͏͏͏͏͏͏͏͏͏͏͏͏͏͏͏͏͏͏͏͏͏͏͏͏͏͏͏͏͏͏͏͏͏͏͏͏͏͏͏͏͏͏͏͏͏͏͏͏͏͏͏͏͏͏͏͏͏͏͏͏͏͏͏͏͏͏͏͏͏͏͏͏͏͏͏͏͏͏͏͏͏͏͏͏͏͏͏͏͏͏͏͏͏͏͏͏͏͏͏͏͏͏͏͏͏͏͏͏͏͏͏͏͏͏͏͏͏͏͏͏͏͏͏͏͏͏͏͏͏͏͏͏͏͏͏͏͏͏͏͏͏͏͏͏͏͏͏͏͏͏͏͏͏͏͏͏͏͏͏͏͏͏͏͏͏͏͏͏͏͏͏͏͏͏͏͏͏͏͏͏͏͏͏͏͏͏͏͏͏͏͏͏͏͏͏͏͏͏͏͏͏͏͏͏͏͏͏͏͏͏͏͏͏͏͏͏͏͏͏͏͏͏͏͏͏͏͏͏͏͏͏͏͏͏͏͏͏͏͏͏͏͏͏͏͏͏͏͏͏͏͏͏͏͏͏͏͏͏͏͏͏͏͏͏͏͏͏͏͏͏͏͏͏͏͏͏͏͏͏͏͏͏͏͏͏͏͏͏͏͏͏͏͏͏͏͏͏͏͏͏͏͏͏͏͏͏͏͏͏͏͏͏͏͏͏͏͏͏͏͏͏͏͏͏͏͏͏͏͏͏͏͏͏͏͏͏͏͏͏͏͏͏͏͏͏͏͏͏͏͏͏͏͏͏͏͏͏͏͏͏͏͏͏͏͏͏͏͏͏͏͏͏͏͏͏͏͏͏͏͏͏͏͏͏͏͏͏͏͏͏͏͏͏͏͏͏͏͏͏͏͏͏͏͏͏͏͏͏͏͏͏͏͏͏͏͏͏͏͏͏͏͏͏͏͏͏͏͏͏͏͏͏͏͏͏͏͏͏͏͏͏͏͏͏͏͏͏͏͏͏͏͏͏͏͏͏͏͏͏͏͏͏͏͏͏͏͏͏͏͏͏͏͏͏͏͏͏͏͏͏͏͏͏͏͏͏͏͏͏͏͏͏͏͏͏͏͏͏͏͏͏͏͏͏͏͏͏͏͏͏͏͏͏͏͏͏͏͏͏͏͏͏͏͏͏͏͏͏͏͏͏͏͏͏͏͏͏͏͏͏͏͏͏͏͏͏͏͏͏͏͏͏͏͏͏͏͏͏͏͏͏͏͏͏͏͏͏͏͏͏͏͏͏͏͏͏͏͏͏͏͏͏͏͏͏͏͏͏͏͏͏͏͏͏͏͏͏͏͏͏͏͏͏͏͏͏͏͏͏͏͏͏͏͏͏͏͏͏͏͏͏͏͏͏͏͏͏͏͏͏͏͏͏͏͏͏͏͏͏͏͏͏͏͏͏͏͏͏͏͏͏͏͏͏͏͏͏͏͏͏͏͏͏͏͏͏͏͏͏͏͏͏͏͏͏͏͏͏͏͏͏͏͏͏͏͏͏͏͏͏͏͏͏͏͏͏͏͏͏͏͏͏͏͏͏͏͏͏͏͏͏͏͏͏͏͏͏͏͏͏͏͏͏͏͏͏͏͏͏͏͏͏͏͏͏͏͏͏͏͏͏͏͏͏͏͏͏͏͏͏͏͏͏͏͏͏͏͏͏͏͏͏͏͏͏͏͏͏͏͏͏͏͏͏͏͏͏͏͏͏͏͏͏͏͏͏͏͏͏͏͏͏͏͏͏͏͏͏͏͏͏͏͏͏͏͏͏͏͏͏͏͏͏͏͏͏͏͏͏͏͏͏͏͏͏͏͏͏͏͏͏͏͏͏͏͏͏͏͏͏͏͏͏͏͏͏͏͏͏͏͏͏͏͏͏͏͏͏͏͏͏͏͏͏͏͏͏͏͏͏͏͏͏͏͏͏͏͏͏͏͏͏͏͏͏͏͏͏͏͏͏͏͏͏͏͏͏͏͏͏͏͏͏͏͏͏͏͏͏͏͏͏͏͏͏͏͏͏͏͏͏͏͏͏͏͏͏͏͏͏͏͏͏͏͏͏͏͏͏͏͏͏͏͏͏͏͏͏͏͏͏͏͏͏͏͏͏͏͏͏͏͏͏͏͏͏͏͏͏͏͏͏͏͏͏͏͏͏͏͏͏͏͏͏͏͏͏͏͏͏͏͏͏͏͏͏͏͏͏͏͏͏͏͏͏͏͏͏͏͏͏͏͏͏͏͏͏͏͏͏͏͏͏͏͏͏͏͏͏͏͏͏͏͏͏͏͏͏͏͏͏͏͏͏͏͏͏͏͏͏͏͏͏͏͏͏͏͏͏͏͏͏͏͏͏͏͏͏͏͏͏͏͏͏͏͏͏͏͏͏͏͏͏͏͏͏͏͏͏͏͏͏͏͏͏͏͏͏͏͏͏͏͏͏͏͏͏͏͏͏͏͏͏͏͏͏͏͏͏͏͏͏͏͏͏͏͏͏͏͏͏͏͏͏͏͏͏͏͏͏͏͏͏͏͏͏͏͏͏͏͏͏͏͏͏͏͏͏͏͏͏͏͏͏͏͏͏͏͏͏͏͏͏͏͏͏͏͏͏͏͏͏͏͏͏͏͏͏͏͏͏͏͏͏͏͏͏͏͏͏͏͏͏͏͏͏͏͏͏͏͏͏͏͏͏͏͏͏͏͏͏͏͏͏͏͏͏͏͏͏͏͏͏͏͏͏͏͏͏͏͏͏͏͏͏͏͏͏͏͏͏͏͏͏͏͏͏͏͏͏͏͏͏͏͏͏͏͏͏͏͏͏͏͏͏͏͏͏͏͏͏͏͏͏͏͏͏͏͏͏͏͏͏͏͏͏͏͏͏͏͏͏͏͏͏͏͏͏͏͏͏͏͏͏͏͏͏͏͏͏͏͏͏͏͏͏͏͏͏͏͏͏͏͏͏͏͏͏͏͏͏͏͏͏͏͏͏͏͏͏͏͏͏͏͏͏͏͏͏͏͏͏͏͏͏͏͏͏͏͏͏͏͏͏͏͏͏͏͏͏͏͏͏͏͏͏͏͏͏͏͏͏͏͏͏͏͏͏͏͏͏͏͏͏͏͏͏͏͏͏͏͏͏͏͏͏͏͏͏͏͏͏͏͏͏͏͏͏͏͏͏͏͏͏͏͏͏͏͏͏͏͏͏͏͏͏͏͏͏͏͏͏͏͏͏͏͏͏͏͏͏͏͏͏͏͏͏͏͏͏͏͏͏͏͏͏͏͏͏͏͏͏͏͏͏͏͏͏͏͏͏͏͏͏͏͏͏͏͏͏͏͏͏͏͏͏͏͏͏͏͏͏͏͏͏͏͏͏͏͏͏͏͏͏͏͏͏͏͏͏͏͏͏͏͏͏͏͏͏͏͏͏͏͏͏͏͏͏͏͏͏͏͏͏͏͏͏͏͏͏͏͏͏͏͏͏͏͏͏͏͏͏͏͏͏͏͏͏͏͏͏͏͏͏͏͏͏͏͏͏͏͏͏͏͏͏͏͏͏͏͏͏͏͏͏͏͏͏͏͏͏͏͏͏͏͏͏͏͏͏͏͏͏͏͏͏͏͏͏͏͏͏͏͏͏͏͏͏͏͏͏͏͏͏͏͏͏͏͏͏͏͏͏͏͏͏͏͏͏͏͏͏͏͏͏͏͏͏͏͏͏͏͏͏͏͏͏͏͏͏͏͏͏͏͏͏͏͏͏͏͏͏͏͏͏͏͏͏͏͏͏͏͏͏͏͏͏͏͏͏͏͏͏͏͏͏͏͏͏͏͏͏͏͏͏͏͏͏͏͏͏͏͏͏͏͏͏͏͏͏͏͏͏͏͏͏͏͏͏͏͏͏͏͏͏͏͏͏͏͏͏͏͏͏͏͏͏͏͏͏͏͏͏͏͏͏͏͏͏͏͏͏͏͏͏͏͏͏͏͏͏͏͏͏͏͏͏͏͏͏͏͏͏͏͏͏͏͏͏͏͏͏͏͏͏͏͏͏͏͏͏͏͏͏͏͏͏͏͏͏͏͏͏͏͏͏͏͏͏͏͏͏͏͏͏͏͏͏͏͏͏͏͏͏͏͏͏͏͏͏͏͏͏͏͏͏͏͏͏͏͏͏͏͏͏͏͏͏͏͏͏͏͏͏͏͏͏͏͏͏͏͏͏͏͏͏͏͏͏͏͏͏͏͏͏͏͏͏͏͏͏͏͏͏͏͏͏͏͏͏͏͏͏͏͏͏͏͏͏͏͏͏͏͏͏͏͏͏͏͏͏͏͏͏͏͏͏͏͏͏͏͏͏͏͏͏͏͏͏͏͏͏͏͏͏͏͏͏͏͏͏͏͏͏͏͏͏͏͏͏͏͏͏͏͏͏͏͏͏͏͏͏͏͏͏͏͏͏͏͏͏͏͏͏͏͏͏͏͏͏͏͏͏͏͏͏͏͏͏͏͏͏͏͏͏͏͏͏͏͏͏͏͏͏͏͏͏͏͏͏͏͏͏͏͏͏͏͏͏͏͏͏͏͏͏͏͏͏͏͏͏͏͏͏͏͏͏͏͏͏͏͏͏͏͏͏͏͏͏͏͏͏͏͏͏͏͏͏͏͏͏͏͏͏͏͏͏͏͏͏͏͏͏͏͏͏͏͏͏͏͏͏͏͏͏͏͏͏͏͏͏͏͏͏͏͏͏͏͏͏͏͏͏͏͏͏͏͏͏͏͏͏͏͏͏͏͏͏͏͏͏͏͏͏͏͏͏͏͏͏͏͏͏͏͏͏͏͏͏͏͏͏͏͏͏͏͏͏͏͏͏͏͏͏͏͏͏͏͏͏͏͏͏͏͏͏͏͏͏͏͏͏͏͏͏͏͏͏͏͏͏͏͏͏͏͏͏͏͏͏͏͏͏͏͏͏͏͏͏͏͏͏͏͏͏͏͏͏͏͏͏͏͏͏͏͏͏͏͏͏͏͏͏͏͏͏͏͏͏͏͏͏͏͏͏͏͏͏͏͏͏͏͏͏͏͏͏͏͏͏͏͏͏͏͏͏͏͏͏͏͏͏͏͏͏͏͏͏͏͏͏͏͏͏͏͏͏͏͏͏͏͏͏͏͏͏͏͏͏͏͏͏͏͏͏͏͏͏͏͏͏͏͏͏͏͏͏͏͏͏͏͏͏͏͏͏͏͏͏͏͏͏͏͏͏͏͏͏͏͏͏͏͏͏͏͏͏͏͏͏͏͏͏͏͏͏͏͏͏͏͏͏͏͏͏͏͏͏͏͏͏͏͏͏͏͏͏͏͏͏͏͏͏͏͏͏͏͏͏͏͏͏͏͏͏͏͏͏͏͏͏͏͏͏͏͏͏͏͏͏͏͏͏͏͏͏͏͏͏͏͏͏͏͏͏͏͏͏͏͏͏͏͏͏͏͏͏͏͏͏͏͏͏͏͏͏͏͏͏͏͏͏͏͏͏͏͏͏͏͏͏͏͏͏͏͏͏͏͏͏͏͏͏͏͏͏͏͏͏͏͏͏͏͏͏͏͏͏͏͏͏͏͏͏͏͏͏͏͏͏͏͏͏͏͏͏͏͏͏͏͏͏͏͏͏͏͏͏͏͏͏͏͏͏͏͏͏͏͏͏͏͏͏͏͏͏͏͏͏͏͏͏͏͏͏͏͏͏͏͏͏͏͏͏͏͏͏͏͏͏͏͏͏͏͏͏͏͏͏͏͏͏͏͏͏͏͏͏͏͏͏͏͏͏͏͏͏͏͏͏͏͏͏͏͏͏͏͏͏͏͏͏͏͏͏͏͏͏͏͏͏͏͏͏͏͏͏͏͏͏͏͏͏͏͏͏͏͏͏͏͏͏͏͏͏͏͏͏͏͏͏͏͏͏͏͏͏͏͏͏͏͏͏͏͏͏͏͏͏͏͏͏͏͏͏͏͏͏͏͏͏͏͏͏͏͏͏͏͏͏͏͏͏͏͏͏͏͏͏͏͏͏͏͏͏͏͏͏͏͏͏͏͏͏͏͏͏͏͏͏͏͏͏͏͏͏͏͏͏͏͏͏͏͏͏͏͏͏͏͏͏͏͏͏͏͏͏͏͏͏͏͏͏͏͏͏͏͏͏͏͏͏͏͏͏͏͏͏͏͏͏͏͏͏͏͏͏͏͏͏͏͏͏͏͏͏͏͏͏͏͏͏͏͏͏͏͏͏͏͏͏͏͏͏͏͏͏͏͏͏͏͏͏͏͏͏͏͏͏͏͏͏͏͏͏͏͏͏͏͏͏͏͏͏͏͏͏͏͏͏͏͏͏͏͏͏͏͏͏͏͏͏͏͏͏͏͏͏͏͏͏͏͏͏͏͏͏͏͏͏͏͏͏͏͏͏͏͏͏͏͏͏͏͏͏͏͏͏͏͏͏͏͏͏͏͏͏͏͏͏͏͏͏͏͏͏͏͏͏͏͏͏͏͏͏͏͏͏͏͏͏͏͏͏͏͏͏͏͏͏͏͏͏͏͏͏͏͏͏͏͏͏͏͏͏͏͏͏͏͏͏͏͏͏͏͏͏͏͏͏͏͏͏͏͏͏͏͏͏͏͏͏͏͏͏͏͏͏͏͏͏͏͏͏͏͏͏͏͏͏͏͏͏͏͏͏͏͏͏͏͏͏͏͏͏͏͏͏͏͏͏͏͏͏͏͏͏͏͏͏͏͏͏͏͏͏͏͏͏͏͏͏͏͏͏͏͏͏͏͏͏͏͏͏͏͏͏͏͏͏͏͏͏͏͏͏͏͏͏͏͏͏͏͏͏͏͏͏͏͏͏͏͏͏͏͏͏͏͏͏͏͏͏͏͏͏͏͏͏͏͏͏͏͏͏͏͏͏͏͏͏͏͏͏͏͏͏͏͏͏͏͏͏͏͏͏͏͏͏͏͏͏͏͏͏͏͏͏͏͏͏͏͏͏͏͏͏͏͏͏͏͏͏͏͏͏͏͏͏͏͏͏͏͏͏͏͏͏͏͏͏͏͏͏͏͏͏͏͏͏͏͏͏͏͏͏͏͏͏͏͏͏͏͏͏͏͏͏͏͏͏͏͏͏͏͏͏͏͏͏͏͏͏͏͏͏͏͏͏͏͏͏͏͏͏͏͏͏͏͏͏͏͏͏͏͏͏͏͏͏͏͏͏͏͏͏͏͏͏͏͏͏͏͏͏͏͏͏͏͏͏͏͏͏͏͏͏͏͏͏͏͏͏͏͏͏͏͏͏͏͏͏͏͏͏͏͏͏͏͏͏͏͏͏͏͏͏͏͏͏͏͏͏͏͏͏͏͏͏͏͏͏͏͏͏͏͏͏͏͏͏͏͏͏͏͏͏͏͏͏͏͏͏͏͏͏͏͏͏͏͏͏͏͏͏͏͏͏͏͏͏͏͏͏͏͏͏͏͏͏͏͏͏͏͏͏͏͏͏͏͏͏͏͏͏͏͏͏͏͏͏͏͏͏͏͏͏͏͏͏͏͏͏͏͏͏͏͏͏͏͏͏͏͏͏͏͏͏͏͏͏͏͏͏͏͏͏͏͏͏͏͏͏͏͏͏͏͏͏͏͏͏͏͏͏͏͏͏͏͏͏͏͏͏͏͏͏͏͏͏͏͏͏͏͏͏͏͏͏͏͏͏͏͏͏͏͏͏͏͏͏͏͏͏͏͏͏͏͏͏͏͏͏͏͏͏͏͏͏͏͏͏͏͏͏͏͏͏͏͏͏͏͏͏͏͏͏͏͏͏͏͏͏͏͏͏͏͏͏͏͏͏͏͏͏͏͏͏͏͏͏͏͏͏͏͏͏͏͏͏͏͏͏͏͏͏͏͏͏͏͏͏͏͏͏͏͏͏͏͏͏͏͏͏͏͏͏͏͏͏͏͏͏͏͏͏͏͏͏͏͏͏͏͏͏͏͏͏͏͏͏͏͏͏͏͏͏͏͏͏͏͏͏͏͏͏͏͏͏͏͏͏͏͏͏͏͏͏͏͏͏͏͏͏͏͏͏͏͏͏͏͏͏͏͏͏͏͏͏͏͏͏͏͏͏͏͏͏͏͏͏͏͏͏͏͏͏͏͏͏͏͏͏͏͏͏͏͏͏͏͏͏͏͏͏͏͏͏͏͏͏͏͏͏͏͏͏͏͏͏͏͏͏͏͏͏͏͏͏͏͏͏͏͏͏͏͏͏͏͏͏͏͏͏͏͏͏͏͏͏͏͏͏͏͏͏͏͏͏͏͏͏͏͏͏͏͏͏͏͏͏͏͏͏͏͏͏͏͏͏͏͏͏͏͏͏͏͏͏͏͏͏͏͏͏͏͏͏͏͏͏͏͏͏͏͏͏͏͏͏͏͏͏͏͏͏͏͏͏͏͏͏͏͏͏͏͏͏͏͏͏͏͏͏͏͏͏͏͏͏͏͏͏͏͏͏͏͏͏͏͏͏͏͏͏͏͏͏͏͏͏͏͏͏͏͏͏͏͏͏͏͏͏͏͏͏͏͏͏͏͏͏͏͏͏͏͏͏͏͏͏͏͏͏͏͏͏͏͏͏͏͏͏͏͏͏͏͏͏͏͏͏͏͏͏͏͏͏͏͏͏͏͏͏͏͏͏͏͏͏͏͏͏͏͏͏͏͏͏͏͏͏͏͏͏͏͏͏͏͏͏͏͏͏͏͏͏͏͏͏͏͏͏͏͏͏͏͏͏͏͏͏͏͏͏͏͏͏͏͏͏͏͏͏͏͏͏͏͏͏͏͏͏͏͏͏͏͏͏͏͏͏͏͏͏͏͏͏͏͏͏͏͏͏͏͏͏͏͏͏͏͏͏͏͏͏͏͏͏͏͏͏͏͏͏͏͏͏͏͏͏͏͏͏͏͏͏͏͏͏͏͏͏͏͏͏͏͏͏͏͏͏͏͏͏͏͏͏͏͏͏͏͏͏͏͏͏͏͏͏͏͏͏͏͏͏͏͏͏͏͏͏͏͏͏͏͏͏͏͏͏͏͏͏͏͏͏͏͏͏͏͏͏͏͏͏͏͏͏͏͏͏͏͏͏͏͏͏͏͏͏͏͏͏͏͏͏͏͏͏͏͏͏͏͏͏͏͏͏͏͏͏͏͏͏͏͏͏͏͏͏͏͏͏͏͏͏͏͏͏͏͏͏͏͏͏͏͏͏͏͏͏͏͏͏͏͏͏͏͏͏͏͏͏͏͏͏͏͏͏͏͏͏͏͏͏͏͏͏͏͏͏͏͏͏͏͏͏͏͏͏͏͏͏͏͏͏͏͏͏͏͏͏͏͏͏͏͏͏͏͏͏͏͏͏͏͏͏͏͏͏͏͏͏͏͏͏͏͏͏͏͏͏͏͏͏͏͏͏͏͏͏͏͏͏͏͏͏͏͏͏͏͏͏͏͏͏͏͏͏͏͏͏͏͏͏͏͏͏͏͏͏͏͏͏͏͏͏͏͏͏͏͏͏͏͏͏͏͏͏͏͏͏͏͏͏͏͏͏͏͏͏͏͏͏͏͏͏͏͏͏͏͏͏͏͏͏͏͏͏͏͏͏͏͏͏͏͏͏͏͏͏͏͏\n65💎 Rp14.700\n129💎 Rp29.000\n194💎\tRp43.500\n323💎 Rp72.500\n388💎 Rp86.000\n530💎\tRp116.000\n595💎 Rp129.000\n724💎 Rp158.000\n853💎 Rp187.000\n\nSeterus nya tanyak admin",
      "isImage": false,
      "image_url": "-"
   },
   {
      "id": "120363041567830603@g.us",
      "key": "DAFTAR E-WALLET",
      "response": "*DAFTAR E-WALLET :*\n\n͏͏͏͏͏͏͏͏͏͏͏͏͏͏͏͏͏͏͏͏͏͏͏͏͏͏͏͏͏͏͏͏͏͏͏͏͏͏͏͏͏͏͏͏͏͏͏͏͏͏͏͏͏͏͏͏͏͏͏͏͏͏͏͏͏͏͏͏͏͏͏͏͏͏͏͏͏͏͏͏͏͏͏͏͏͏͏͏͏͏͏͏͏͏͏͏͏͏͏͏͏͏͏͏͏͏͏͏͏͏͏͏͏͏͏͏͏͏͏͏͏͏͏͏͏͏͏͏͏͏͏͏͏͏͏͏͏͏͏͏͏͏͏͏͏͏͏͏͏͏͏͏͏͏͏͏͏͏͏͏͏͏͏͏͏͏͏͏͏͏͏͏͏͏͏͏͏͏͏͏͏͏͏͏͏͏͏͏͏͏͏͏͏͏͏͏͏͏͏͏͏͏͏͏͏͏͏͏͏͏͏͏͏͏͏͏͏͏͏͏͏͏͏͏͏͏͏͏͏͏͏͏͏͏͏͏͏͏͏͏͏͏͏͏͏͏͏͏͏͏͏͏͏͏͏͏͏͏͏͏͏͏͏͏͏͏͏͏͏͏͏͏͏͏͏͏͏͏͏͏͏͏͏͏͏͏͏͏͏͏͏͏͏͏͏͏͏͏͏͏͏͏͏͏͏͏͏͏͏͏͏͏͏͏͏͏͏͏͏͏͏͏͏͏͏͏͏͏͏͏͏͏͏͏͏͏͏͏͏͏͏͏͏͏͏͏͏͏͏͏͏͏͏͏͏͏͏͏͏͏͏͏͏͏͏͏͏͏͏͏͏͏͏͏͏͏͏͏͏͏͏͏͏͏͏͏͏͏͏͏͏͏͏͏͏͏͏͏͏͏͏͏͏͏͏͏͏͏͏͏͏͏͏͏͏͏͏͏͏͏͏͏͏͏͏͏͏͏͏͏͏͏͏͏͏͏͏͏͏͏͏͏͏͏͏͏͏͏͏͏͏͏͏͏͏͏͏͏͏͏͏͏͏͏͏͏͏͏͏͏͏͏͏͏͏͏͏͏͏͏͏͏͏͏͏͏͏͏͏͏͏͏͏͏͏͏͏͏͏͏͏͏͏͏͏͏͏͏͏͏͏͏͏͏͏͏͏͏͏͏͏͏͏͏͏͏͏͏͏͏͏͏͏͏͏͏͏͏͏͏͏͏͏͏͏͏͏͏͏͏͏͏͏͏͏͏͏͏͏͏͏͏͏͏͏͏͏͏͏͏͏͏͏͏͏͏͏͏͏͏͏͏͏͏͏͏͏͏͏͏͏͏͏͏͏͏͏͏͏͏͏͏͏͏͏͏͏͏͏͏͏͏͏͏͏͏͏͏͏͏͏͏͏͏͏͏͏͏͏͏͏͏͏͏͏͏͏͏͏͏͏͏͏͏͏͏͏͏͏͏͏͏͏͏͏͏͏͏͏͏͏͏͏͏͏͏͏͏͏͏͏͏͏͏͏͏͏͏͏͏͏͏͏͏͏͏͏͏͏͏͏͏͏͏͏͏͏͏͏͏͏͏͏͏͏͏͏͏͏͏͏͏͏͏͏͏͏͏͏͏͏͏͏͏͏͏͏͏͏͏͏͏͏͏͏͏͏͏͏͏͏͏͏͏͏͏͏͏͏͏͏͏͏͏͏͏͏͏͏͏͏͏͏͏͏͏͏͏͏͏͏͏͏͏͏͏͏͏͏͏͏͏͏͏͏͏͏͏͏͏͏͏͏͏͏͏͏͏͏͏͏͏͏͏͏͏͏͏͏͏͏͏͏͏͏͏͏͏͏͏͏͏͏͏͏͏͏͏͏͏͏͏͏͏͏͏͏͏͏͏͏͏͏͏͏͏͏͏͏͏͏͏͏͏͏͏͏͏͏͏͏͏͏͏͏͏͏͏͏͏͏͏͏͏͏͏͏͏͏͏͏͏͏͏͏͏͏͏͏͏͏͏͏͏͏͏͏͏͏͏͏͏͏͏͏͏͏͏͏͏͏͏͏͏͏͏͏͏͏͏͏͏͏͏͏͏͏͏͏͏͏͏͏͏͏͏͏͏͏͏͏͏͏͏͏͏͏͏͏͏͏͏͏͏͏͏͏͏͏͏͏͏͏͏͏͏͏͏͏͏͏͏͏͏͏͏͏͏͏͏͏͏͏͏͏͏͏͏͏͏͏͏͏͏͏͏͏͏͏͏͏͏͏͏͏͏͏͏͏͏͏͏͏͏͏͏͏͏͏͏͏͏͏͏͏͏͏͏͏͏͏͏͏͏͏͏͏͏͏͏͏͏͏͏͏͏͏͏͏͏͏͏͏͏͏͏͏͏͏͏͏͏͏͏͏͏͏͏͏͏͏͏͏͏͏͏͏͏͏͏͏͏͏͏͏͏͏͏͏͏͏͏͏͏͏͏͏͏͏͏͏͏͏͏͏͏͏͏͏͏͏͏͏͏͏͏͏͏͏͏͏͏͏͏͏͏͏͏͏͏͏͏͏͏͏͏͏͏͏͏͏͏͏͏͏͏͏͏͏͏͏͏͏͏͏͏͏͏͏͏͏͏͏͏͏͏͏͏͏͏͏͏͏͏͏͏͏͏͏͏͏͏͏͏͏͏͏͏͏͏͏͏͏͏͏͏͏͏͏͏͏͏͏͏͏͏͏͏͏͏͏͏͏͏͏͏͏͏͏͏͏͏͏͏͏͏͏͏͏͏͏͏͏͏͏͏͏͏͏͏͏͏͏͏͏͏͏͏͏͏͏͏͏͏͏͏͏͏͏͏͏͏͏͏͏͏͏͏͏͏͏͏͏͏͏͏͏͏͏͏͏͏͏͏͏͏͏͏͏͏͏͏͏͏͏͏͏͏͏͏͏͏͏͏͏͏͏͏͏͏͏͏͏͏͏͏͏͏͏͏͏͏͏͏͏͏͏͏͏͏͏͏͏͏͏͏͏͏͏͏͏͏͏͏͏͏͏͏͏͏͏͏͏͏͏͏͏͏͏͏͏͏͏͏͏͏͏͏͏͏͏͏͏͏͏͏͏͏͏͏͏͏͏͏͏͏͏͏͏͏͏͏͏͏͏͏͏͏͏͏͏͏͏͏͏͏͏͏͏͏͏͏͏͏͏͏͏͏͏͏͏͏͏͏͏͏͏͏͏͏͏͏͏͏͏͏͏͏͏͏͏͏͏͏͏͏͏͏͏͏͏͏͏͏͏͏͏͏͏͏͏͏͏͏͏͏͏͏͏͏͏͏͏͏͏͏͏͏͏͏͏͏͏͏͏͏͏͏͏͏͏͏͏͏͏͏͏͏͏͏͏͏͏͏͏͏͏͏͏͏͏͏͏͏͏͏͏͏͏͏͏͏͏͏͏͏͏͏͏͏͏͏͏͏͏͏͏͏͏͏͏͏͏͏͏͏͏͏͏͏͏͏͏͏͏͏͏͏͏͏͏͏͏͏͏͏͏͏͏͏͏͏͏͏͏͏͏͏͏͏͏͏͏͏͏͏͏͏͏͏͏͏͏͏͏͏͏͏͏͏͏͏͏͏͏͏͏͏͏͏͏͏͏͏͏͏͏͏͏͏͏͏͏͏͏͏͏͏͏͏͏͏͏͏͏͏͏͏͏͏͏͏͏͏͏͏͏͏͏͏͏͏͏͏͏͏͏͏͏͏͏͏͏͏͏͏͏͏͏͏͏͏͏͏͏͏͏͏͏͏͏͏͏͏͏͏͏͏͏͏͏͏͏͏͏͏͏͏͏͏͏͏͏͏͏͏͏͏͏͏͏͏͏͏͏͏͏͏͏͏͏͏͏͏͏͏͏͏͏͏͏͏͏͏͏͏͏͏͏͏͏͏͏͏͏͏͏͏͏͏͏͏͏͏͏͏͏͏͏͏͏͏͏͏͏͏͏͏͏͏͏͏͏͏͏͏͏͏͏͏͏͏͏͏͏͏͏͏͏͏͏͏͏͏͏͏͏͏͏͏͏͏͏͏͏͏͏͏͏͏͏͏͏͏͏͏͏͏͏͏͏͏͏͏͏͏͏͏͏͏͏͏͏͏͏͏͏͏͏͏͏͏͏͏͏͏͏͏͏͏͏͏͏͏͏͏͏͏͏͏͏͏͏͏͏͏͏͏͏͏͏͏͏͏͏͏͏͏͏͏͏͏͏͏͏͏͏͏͏͏͏͏͏͏͏͏͏͏͏͏͏͏͏͏͏͏͏͏͏͏͏͏͏͏͏͏͏͏͏͏͏͏͏͏͏͏͏͏͏͏͏͏͏͏͏͏͏͏͏͏͏͏͏͏͏͏͏͏͏͏͏͏͏͏͏͏͏͏͏͏͏͏͏͏͏͏͏͏͏͏͏͏͏͏͏͏͏͏͏͏͏͏͏͏͏͏͏͏͏͏͏͏͏͏͏͏͏͏͏͏͏͏͏͏͏͏͏͏͏͏͏͏͏͏͏͏͏͏͏͏͏͏͏͏͏͏͏͏͏͏͏͏͏͏͏͏͏͏͏͏͏͏͏͏͏͏͏͏͏͏͏͏͏͏͏͏͏͏͏͏͏͏͏͏͏͏͏͏͏͏͏͏͏͏͏͏͏͏͏͏͏͏͏͏͏͏͏͏͏͏͏͏͏͏͏͏͏͏͏͏͏͏͏͏͏͏͏͏͏͏͏͏͏͏͏͏͏͏͏͏͏͏͏͏͏͏͏͏͏͏͏͏͏͏͏͏͏͏͏͏͏͏͏͏͏͏͏͏͏͏͏͏͏͏͏͏͏͏͏͏͏͏͏͏͏͏͏͏͏͏͏͏͏͏͏͏͏͏͏͏͏͏͏͏͏͏͏͏͏͏͏͏͏͏͏͏͏͏͏͏͏͏͏͏͏͏͏͏͏͏͏͏͏͏͏͏͏͏͏͏͏͏͏͏͏͏͏͏͏͏͏͏͏͏͏͏͏͏͏͏͏͏͏͏͏͏͏͏͏͏͏͏͏͏͏͏͏͏͏͏͏͏͏͏͏͏͏͏͏͏͏͏͏͏͏͏͏͏͏͏͏͏͏͏͏͏͏͏͏͏͏͏͏͏͏͏͏͏͏͏͏͏͏͏͏͏͏͏͏͏͏͏͏͏͏͏͏͏͏͏͏͏͏͏͏͏͏͏͏͏͏͏͏͏͏͏͏͏͏͏͏͏͏͏͏͏͏͏͏͏͏͏͏͏͏͏͏͏͏͏͏͏͏͏͏͏͏͏͏͏͏͏͏͏͏͏͏͏͏͏͏͏͏͏͏͏͏͏͏͏͏͏͏͏͏͏͏͏͏͏͏͏͏͏͏͏͏͏͏͏͏͏͏͏͏͏͏͏͏͏͏͏͏͏͏͏͏͏͏͏͏͏͏͏͏͏͏͏͏͏͏͏͏͏͏͏͏͏͏͏͏͏͏͏͏͏͏͏͏͏͏͏͏͏͏͏͏͏͏͏͏͏͏͏͏͏͏͏͏͏͏͏͏͏͏͏͏͏͏͏͏͏͏͏͏͏͏͏͏͏͏͏͏͏͏͏͏͏͏͏͏͏͏͏͏͏͏͏͏͏͏͏͏͏͏͏͏͏͏͏͏͏͏͏͏͏͏͏͏͏͏͏͏͏͏͏͏͏͏͏͏͏͏͏͏͏͏͏͏͏͏͏͏͏͏͏͏͏͏͏͏͏͏͏͏͏͏͏͏͏͏͏͏͏͏͏͏͏͏͏͏͏͏͏͏͏͏͏͏͏͏͏͏͏͏͏͏͏͏͏͏͏͏͏͏͏͏͏͏͏͏͏͏͏͏͏͏͏͏͏͏͏͏͏͏͏͏͏͏͏͏͏͏͏͏͏͏͏͏͏͏͏͏͏͏͏͏͏͏͏͏͏͏͏͏͏͏͏͏͏͏͏͏͏͏͏͏͏͏͏͏͏͏͏͏͏͏͏͏͏͏͏͏͏͏͏͏͏͏͏͏͏͏͏͏͏͏͏͏͏͏͏͏͏͏͏͏͏͏͏͏͏͏͏͏͏͏͏͏͏͏͏͏͏͏͏͏͏͏͏͏͏͏͏͏͏͏͏͏͏͏͏͏͏͏͏͏͏͏͏͏͏͏͏͏͏͏͏͏͏͏͏͏͏͏͏͏͏͏͏͏͏͏͏͏͏͏͏͏͏͏͏͏͏͏͏͏͏͏͏͏͏͏͏͏͏͏͏͏͏͏͏͏͏͏͏͏͏͏͏͏͏͏͏͏͏͏͏͏͏͏͏͏͏͏͏͏͏͏͏͏͏͏͏͏͏͏͏͏͏͏͏͏͏͏͏͏͏͏͏͏͏͏͏͏͏͏͏͏͏͏͏͏͏͏͏͏͏͏͏͏͏͏͏͏͏͏͏͏͏͏͏͏͏͏͏͏͏͏͏͏͏͏͏͏͏͏͏͏͏͏͏͏͏͏͏͏͏͏͏͏͏͏͏͏͏͏͏͏͏͏͏͏͏͏͏͏͏͏͏͏͏͏͏͏͏͏͏͏͏͏͏͏͏͏͏͏͏͏͏͏͏͏͏͏͏͏͏͏͏͏͏͏͏͏͏͏͏͏͏͏͏͏͏͏͏͏͏͏͏͏͏͏͏͏͏͏͏͏͏͏͏͏͏͏͏͏͏͏͏͏͏͏͏͏͏͏͏͏͏͏͏͏͏͏͏͏͏͏͏͏͏͏͏͏͏͏͏͏͏͏͏͏͏͏͏͏͏͏͏͏͏͏͏͏͏͏͏͏͏͏͏͏͏͏͏͏͏͏͏͏͏͏͏͏͏͏͏͏͏͏͏͏͏͏͏͏͏͏͏͏͏͏͏͏͏͏͏͏͏͏͏͏͏͏͏͏͏͏͏͏͏͏͏͏͏͏͏͏͏͏͏͏͏͏͏͏͏͏͏͏͏͏͏͏͏͏͏͏͏͏͏͏͏͏͏͏͏͏͏͏͏͏͏͏͏͏͏͏͏͏͏͏͏͏͏͏͏͏͏͏͏͏͏͏͏͏͏͏͏͏͏͏͏͏͏͏͏͏͏͏͏͏͏͏͏͏͏͏͏͏͏͏͏͏͏͏͏͏͏͏͏͏͏͏͏͏͏͏͏͏͏͏͏͏͏͏͏͏͏͏͏͏͏͏͏͏͏͏͏͏͏͏͏͏͏͏͏͏͏͏͏͏͏͏͏͏͏͏͏͏͏͏͏͏͏͏͏͏͏͏͏͏͏͏͏͏͏͏͏͏͏͏͏͏͏͏͏͏͏͏͏͏͏͏͏͏͏͏͏͏͏͏͏͏͏͏͏͏͏͏͏͏͏͏͏͏͏͏͏͏͏͏͏͏͏͏͏͏͏͏͏͏͏͏͏͏͏͏͏͏͏͏͏͏͏͏͏͏͏͏͏͏͏͏͏͏͏͏͏͏͏͏͏͏͏͏͏͏͏͏͏͏͏͏͏͏͏͏͏͏͏͏͏͏͏͏͏͏͏͏͏͏͏͏͏͏͏͏͏͏͏͏͏͏͏͏͏͏͏͏͏͏͏͏͏͏͏͏͏͏͏͏͏͏͏͏͏͏͏͏͏͏͏͏͏͏͏͏͏͏͏͏͏͏͏͏͏͏͏͏͏͏͏͏͏͏͏͏͏͏͏͏͏͏͏͏͏͏͏͏͏͏͏͏͏͏͏͏͏͏͏͏͏͏͏͏͏͏͏͏͏͏͏͏͏͏͏͏͏͏͏͏͏͏͏͏͏͏͏͏͏͏͏͏͏͏͏͏͏͏͏͏͏͏͏͏͏͏͏͏͏͏͏͏͏͏͏͏͏͏͏͏͏͏͏͏͏͏͏͏͏͏͏͏͏͏͏͏͏͏͏͏͏͏͏͏͏͏͏͏͏͏͏͏͏͏͏͏͏͏͏͏͏͏͏͏͏͏͏͏͏͏͏͏͏͏͏͏͏͏͏͏͏͏͏͏͏͏͏͏͏͏͏͏͏͏͏͏͏͏͏͏͏͏͏͏͏͏͏͏͏͏͏͏͏͏͏͏͏͏͏͏͏͏͏͏͏͏͏͏͏͏͏͏͏͏͏͏͏͏͏͏͏͏͏͏͏͏͏͏͏͏͏͏͏͏͏͏͏͏͏͏͏͏͏͏͏͏͏͏͏͏͏͏͏͏͏͏͏͏͏͏͏͏͏͏͏͏͏͏͏͏͏͏͏͏͏͏͏͏͏͏͏͏͏͏͏͏͏͏͏͏͏͏͏͏͏͏͏͏͏͏͏͏͏͏͏͏͏͏͏͏͏͏͏͏͏͏͏͏͏͏͏͏͏͏͏͏͏͏͏͏͏͏͏͏͏͏͏͏͏͏͏͏͏͏͏͏͏͏͏͏͏͏͏͏͏͏͏͏͏͏͏͏͏͏͏͏͏͏͏͏͏͏͏͏͏͏͏͏͏͏͏͏͏͏͏͏͏͏͏͏͏͏͏͏͏͏͏͏͏͏͏͏͏͏͏͏͏͏͏͏͏͏͏͏͏͏͏͏͏͏͏͏͏͏͏͏͏͏͏͏͏͏͏͏͏͏͏͏͏͏͏͏͏͏͏͏͏͏͏͏͏͏͏͏͏͏͏͏͏͏͏͏͏͏͏͏͏͏͏͏͏͏͏͏͏͏͏͏͏͏͏͏͏͏͏͏͏͏͏͏͏͏͏͏͏͏͏͏͏͏͏͏͏͏͏͏͏͏͏͏͏͏͏͏͏͏͏͏͏͏͏͏͏͏͏͏͏͏͏͏͏͏͏͏͏͏͏͏͏͏͏͏͏͏͏͏͏͏͏͏͏͏͏͏͏͏͏͏͏͏͏͏͏͏͏͏͏͏͏͏͏͏͏͏͏͏͏͏͏͏͏͏͏͏͏͏͏͏͏͏͏͏͏͏͏͏͏͏͏͏͏͏͏͏͏͏͏͏͏͏͏͏͏͏͏͏͏͏͏͏͏͏͏͏͏͏͏͏͏͏͏͏͏͏͏͏͏͏͏͏͏͏͏͏͏͏͏͏͏͏͏͏͏͏͏͏͏͏͏͏͏͏͏͏͏͏͏͏͏͏͏͏͏͏͏͏͏͏͏͏͏͏͏͏͏͏͏͏͏͏͏͏͏͏͏͏͏͏͏͏͏͏͏͏͏͏͏͏͏͏͏͏͏͏͏͏͏͏͏͏͏͏͏͏͏͏͏͏͏͏͏͏͏͏͏͏͏͏͏͏͏͏͏͏͏͏͏͏͏͏͏͏͏͏͏͏͏͏͏͏͏͏͏͏͏͏͏͏͏͏͏͏͏͏͏͏͏͏͏͏͏͏͏͏͏͏͏͏͏͏͏͏͏͏͏͏͏͏͏͏͏͏͏͏͏͏͏͏͏͏͏͏͏͏͏͏͏͏͏͏͏͏͏͏͏͏͏͏͏͏͏͏͏͏͏͏͏͏͏͏͏͏͏͏͏͏͏͏͏͏͏͏͏͏͏͏͏͏͏͏͏͏͏͏͏͏͏͏͏͏͏͏͏͏͏͏͏͏͏͏͏͏͏͏͏͏͏͏͏͏͏͏͏͏͏͏͏͏͏͏͏͏͏͏͏͏͏͏͏͏͏͏͏͏͏͏͏͏͏͏͏͏͏͏͏͏͏͏͏͏͏͏͏͏͏͏͏͏͏͏͏͏͏͏͏͏͏͏͏͏͏͏͏͏͏͏͏͏͏͏͏͏͏͏͏͏͏͏͏͏͏͏͏͏͏͏͏͏͏͏͏͏͏͏͏͏͏͏͏͏͏͏͏͏͏͏͏͏͏͏͏͏͏͏͏͏͏͏͏͏͏͏͏͏͏͏͏͏͏͏͏͏͏͏͏͏͏͏͏͏͏͏͏͏͏͏͏͏͏͏͏͏͏͏͏͏͏͏͏͏͏͏͏͏͏͏͏͏͏͏͏͏͏͏͏͏͏͏͏͏͏͏͏͏͏͏͏͏͏͏͏͏͏͏͏͏͏͏͏͏͏͏͏͏͏͏͏͏͏͏͏͏͏͏͏͏͏͏͏͏͏͏͏͏͏͏͏͏͏͏͏͏͏͏͏͏͏͏͏͏͏͏͏͏͏͏͏͏͏͏͏͏͏͏͏͏͏͏͏͏͏͏͏͏͏͏͏͏͏͏͏͏͏͏͏͏͏͏͏͏͏͏͏͏͏͏͏͏͏͏͏͏͏͏͏͏͏͏͏͏͏͏͏͏͏͏͏͏͏͏͏͏͏͏͏͏͏͏͏͏͏͏͏͏͏͏͏͏͏͏͏͏͏͏͏͏͏͏͏͏͏͏͏͏͏͏͏͏͏͏͏͏͏͏͏͏͏͏͏͏͏͏͏͏͏͏͏͏͏͏͏͏͏͏͏͏͏͏͏͏͏͏͏͏͏͏͏͏͏͏͏͏͏͏͏͏͏͏͏͏͏͏͏͏͏͏͏͏͏͏͏͏͏͏͏͏͏͏͏͏͏͏͏͏͏͏͏͏͏͏͏͏͏͏͏͏͏͏͏͏͏͏͏͏͏͏͏͏͏͏͏͏͏͏͏͏͏͏͏͏͏͏͏͏͏͏͏͏͏͏͏͏͏͏\n- M-Bank :\nBCA         :  \nMandiri   : \n\n- Dana     :  081361340807 ahmad zaky\n\n- Gopay   :  081361340807 ahmad zaky\n\n- Ovo        : 081361340807 ahmad zaky\n\n- Shopee : 081361340807 ahmad zaky\n\n- LinkAja :  \n\n- Alfamart / Indomaret Minta Kode dari admin\n\n- Scan Qris Jika E-Wallet Belum Premium (Maaf lagi error) \n*HARUS KIRIM BUKTI*",
      "isImage": false,
      "image_url": "-"
   },
   {
      "id": "120363041567830603@g.us",
      "key": "MLBB GIFT",
      "response": "_*MLBB GIFT*_\n269   💎\tNORMAL  = 36.315\n399   💎\tELITE  = 53.865\n599   💎\tELITE  = 80.865\n749   💎\tSPECIAL  = 101.115\n899   💎\tEPIC  = 121.365\n1089 💎 LOGHTBORN  =147.015\n\nPERGIVE + 3 - 5K\n\n*GIFT ITEM*\n109   💎 EMOTE  = 14.715\n239   💎 CHANGE NAME  = 32.365\n299   💎SQ CHANGE NAME  = 40.365\n199   💎 CREATE SQUAD  = 26.865\n1000💎 CHANGE FLAG  = 135.000\n599   💎 ALL HERO  =80.865\n\nPERGIVE TAMBAH 3 - 5K\n\nRULES :\n- BERTEMAN 7 HARI\n- SEND SESUAI JADWAL/ANTRIAN\n- START KIRIM JAM 19.00 WIB",
      "isImage": false,
      "image_url": "-"
   },
   {
      "id": "120363041567830603@g.us",
      "key": "SQUAD VERIFIKASI",
      "response": "_*Squad Verifikasi*_\nVia ID SQUAD/INVITE\n\n͏͏͏͏͏͏͏͏͏͏͏͏͏͏͏͏͏͏͏͏͏͏͏͏͏͏͏͏͏͏͏͏͏͏͏͏͏͏͏͏͏͏͏͏͏͏͏͏͏͏͏͏͏͏͏͏͏͏͏͏͏͏͏͏͏͏͏͏͏͏͏͏͏͏͏͏͏͏͏͏͏͏͏͏͏͏͏͏͏͏͏͏͏͏͏͏͏͏͏͏͏͏͏͏͏͏͏͏͏͏͏͏͏͏͏͏͏͏͏͏͏͏͏͏͏͏͏͏͏͏͏͏͏͏͏͏͏͏͏͏͏͏͏͏͏͏͏͏͏͏͏͏͏͏͏͏͏͏͏͏͏͏͏͏͏͏͏͏͏͏͏͏͏͏͏͏͏͏͏͏͏͏͏͏͏͏͏͏͏͏͏͏͏͏͏͏͏͏͏͏͏͏͏͏͏͏͏͏͏͏͏͏͏͏͏͏͏͏͏͏͏͏͏͏͏͏͏͏͏͏͏͏͏͏͏͏͏͏͏͏͏͏͏͏͏͏͏͏͏͏͏͏͏͏͏͏͏͏͏͏͏͏͏͏͏͏͏͏͏͏͏͏͏͏͏͏͏͏͏͏͏͏͏͏͏͏͏͏͏͏͏͏͏͏͏͏͏͏͏͏͏͏͏͏͏͏͏͏͏͏͏͏͏͏͏͏͏͏͏͏͏͏͏͏͏͏͏͏͏͏͏͏͏͏͏͏͏͏͏͏͏͏͏͏͏͏͏͏͏͏͏͏͏͏͏͏͏͏͏͏͏͏͏͏͏͏͏͏͏͏͏͏͏͏͏͏͏͏͏͏͏͏͏͏͏͏͏͏͏͏͏͏͏͏͏͏͏͏͏͏͏͏͏͏͏͏͏͏͏͏͏͏͏͏͏͏͏͏͏͏͏͏͏͏͏͏͏͏͏͏͏͏͏͏͏͏͏͏͏͏͏͏͏͏͏͏͏͏͏͏͏͏͏͏͏͏͏͏͏͏͏͏͏͏͏͏͏͏͏͏͏͏͏͏͏͏͏͏͏͏͏͏͏͏͏͏͏͏͏͏͏͏͏͏͏͏͏͏͏͏͏͏͏͏͏͏͏͏͏͏͏͏͏͏͏͏͏͏͏͏͏͏͏͏͏͏͏͏͏͏͏͏͏͏͏͏͏͏͏͏͏͏͏͏͏͏͏͏͏͏͏͏͏͏͏͏͏͏͏͏͏͏͏͏͏͏͏͏͏͏͏͏͏͏͏͏͏͏͏͏͏͏͏͏͏͏͏͏͏͏͏͏͏͏͏͏͏͏͏͏͏͏͏͏͏͏͏͏͏͏͏͏͏͏͏͏͏͏͏͏͏͏͏͏͏͏͏͏͏͏͏͏͏͏͏͏͏͏͏͏͏͏͏͏͏͏͏͏͏͏͏͏͏͏͏͏͏͏͏͏͏͏͏͏͏͏͏͏͏͏͏͏͏͏͏͏͏͏͏͏͏͏͏͏͏͏͏͏͏͏͏͏͏͏͏͏͏͏͏͏͏͏͏͏͏͏͏͏͏͏͏͏͏͏͏͏͏͏͏͏͏͏͏͏͏͏͏͏͏͏͏͏͏͏͏͏͏͏͏͏͏͏͏͏͏͏͏͏͏͏͏͏͏͏͏͏͏͏͏͏͏͏͏͏͏͏͏͏͏͏͏͏͏͏͏͏͏͏͏͏͏͏͏͏͏͏͏͏͏͏͏͏͏͏͏͏͏͏͏͏͏͏͏͏͏͏͏͏͏͏͏͏͏͏͏͏͏͏͏͏͏͏͏͏͏͏͏͏͏͏͏͏͏͏͏͏͏͏͏͏͏͏͏͏͏͏͏͏͏͏͏͏͏͏͏͏͏͏͏͏͏͏͏͏͏͏͏͏͏͏͏͏͏͏͏͏͏͏͏͏͏͏͏͏͏͏͏͏͏͏͏͏͏͏͏͏͏͏͏͏͏͏͏͏͏͏͏͏͏͏͏͏͏͏͏͏͏͏͏͏͏͏͏͏͏͏͏͏͏͏͏͏͏͏͏͏͏͏͏͏͏͏͏͏͏͏͏͏͏͏͏͏͏͏͏͏͏͏͏͏͏͏͏͏͏͏͏͏͏͏͏͏͏͏͏͏͏͏͏͏͏͏͏͏͏͏͏͏͏͏͏͏͏͏͏͏͏͏͏͏͏͏͏͏͏͏͏͏͏͏͏͏͏͏͏͏͏͏͏͏͏͏͏͏͏͏͏͏͏͏͏͏͏͏͏͏͏͏͏͏͏͏͏͏͏͏͏͏͏͏͏͏͏͏͏͏͏͏͏͏͏͏͏͏͏͏͏͏͏͏͏͏͏͏͏͏͏͏͏͏͏͏͏͏͏͏͏͏͏͏͏͏͏͏͏͏͏͏͏͏͏͏͏͏͏͏͏͏͏͏͏͏͏͏͏͏͏͏͏͏͏͏͏͏͏͏͏͏͏͏͏͏͏͏͏͏͏͏͏͏͏͏͏͏͏͏͏͏͏͏͏͏͏͏͏͏͏͏͏͏͏͏͏͏͏͏͏͏͏͏͏͏͏͏͏͏͏͏͏͏͏͏͏͏͏͏͏͏͏͏͏͏͏͏͏͏͏͏͏͏͏͏͏͏͏͏͏͏͏͏͏͏͏͏͏͏͏͏͏͏͏͏͏͏͏͏͏͏͏͏͏͏͏͏͏͏͏͏͏͏͏͏͏͏͏͏͏͏͏͏͏͏͏͏͏͏͏͏͏͏͏͏͏͏͏͏͏͏͏͏͏͏͏͏͏͏͏͏͏͏͏͏͏͏͏͏͏͏͏͏͏͏͏͏͏͏͏͏͏͏͏͏͏͏͏͏͏͏͏͏͏͏͏͏͏͏͏͏͏͏͏͏͏͏͏͏͏͏͏͏͏͏͏͏͏͏͏͏͏͏͏͏͏͏͏͏͏͏͏͏͏͏͏͏͏͏͏͏͏͏͏͏͏͏͏͏͏͏͏͏͏͏͏͏͏͏͏͏͏͏͏͏͏͏͏͏͏͏͏͏͏͏͏͏͏͏͏͏͏͏͏͏͏͏͏͏͏͏͏͏͏͏͏͏͏͏͏͏͏͏͏͏͏͏͏͏͏͏͏͏͏͏͏͏͏͏͏͏͏͏͏͏͏͏͏͏͏͏͏͏͏͏͏͏͏͏͏͏͏͏͏͏͏͏͏͏͏͏͏͏͏͏͏͏͏͏͏͏͏͏͏͏͏͏͏͏͏͏͏͏͏͏͏͏͏͏͏͏͏͏͏͏͏͏͏͏͏͏͏͏͏͏͏͏͏͏͏͏͏͏͏͏͏͏͏͏͏͏͏͏͏͏͏͏͏͏͏͏͏͏͏͏͏͏͏͏͏͏͏͏͏͏͏͏͏͏͏͏͏͏͏͏͏͏͏͏͏͏͏͏͏͏͏͏͏͏͏͏͏͏͏͏͏͏͏͏͏͏͏͏͏͏͏͏͏͏͏͏͏͏͏͏͏͏͏͏͏͏͏͏͏͏͏͏͏͏͏͏͏͏͏͏͏͏͏͏͏͏͏͏͏͏͏͏͏͏͏͏͏͏͏͏͏͏͏͏͏͏͏͏͏͏͏͏͏͏͏͏͏͏͏͏͏͏͏͏͏͏͏͏͏͏͏͏͏͏͏͏͏͏͏͏͏͏͏͏͏͏͏͏͏͏͏͏͏͏͏͏͏͏͏͏͏͏͏͏͏͏͏͏͏͏͏͏͏͏͏͏͏͏͏͏͏͏͏͏͏͏͏͏͏͏͏͏͏͏͏͏͏͏͏͏͏͏͏͏͏͏͏͏͏͏͏͏͏͏͏͏͏͏͏͏͏͏͏͏͏͏͏͏͏͏͏͏͏͏͏͏͏͏͏͏͏͏͏͏͏͏͏͏͏͏͏͏͏͏͏͏͏͏͏͏͏͏͏͏͏͏͏͏͏͏͏͏͏͏͏͏͏͏͏͏͏͏͏͏͏͏͏͏͏͏͏͏͏͏͏͏͏͏͏͏͏͏͏͏͏͏͏͏͏͏͏͏͏͏͏͏͏͏͏͏͏͏͏͏͏͏͏͏͏͏͏͏͏͏͏͏͏͏͏͏͏͏͏͏͏͏͏͏͏͏͏͏͏͏͏͏͏͏͏͏͏͏͏͏͏͏͏͏͏͏͏͏͏͏͏͏͏͏͏͏͏͏͏͏͏͏͏͏͏͏͏͏͏͏͏͏͏͏͏͏͏͏͏͏͏͏͏͏͏͏͏͏͏͏͏͏͏͏͏͏͏͏͏͏͏͏͏͏͏͏͏͏͏͏͏͏͏͏͏͏͏͏͏͏͏͏͏͏͏͏͏͏͏͏͏͏͏͏͏͏͏͏͏͏͏͏͏͏͏͏͏͏͏͏͏͏͏͏͏͏͏͏͏͏͏͏͏͏͏͏͏͏͏͏͏͏͏͏͏͏͏͏͏͏͏͏͏͏͏͏͏͏͏͏͏͏͏͏͏͏͏͏͏͏͏͏͏͏͏͏͏͏͏͏͏͏͏͏͏͏͏͏͏͏͏͏͏͏͏͏͏͏͏͏͏͏͏͏͏͏͏͏͏͏͏͏͏͏͏͏͏͏͏͏͏͏͏͏͏͏͏͏͏͏͏͏͏͏͏͏͏͏͏͏͏͏͏͏͏͏͏͏͏͏͏͏͏͏͏͏͏͏͏͏͏͏͏͏͏͏͏͏͏͏͏͏͏͏͏͏͏͏͏͏͏͏͏͏͏͏͏͏͏͏͏͏͏͏͏͏͏͏͏͏͏͏͏͏͏͏͏͏͏͏͏͏͏͏͏͏͏͏͏͏͏͏͏͏͏͏͏͏͏͏͏͏͏͏͏͏͏͏͏͏͏͏͏͏͏͏͏͏͏͏͏͏͏͏͏͏͏͏͏͏͏͏͏͏͏͏͏͏͏͏͏͏͏͏͏͏͏͏͏͏͏͏͏͏͏͏͏͏͏͏͏͏͏͏͏͏͏͏͏͏͏͏͏͏͏͏͏͏͏͏͏͏͏͏͏͏͏͏͏͏͏͏͏͏͏͏͏͏͏͏͏͏͏͏͏͏͏͏͏͏͏͏͏͏͏͏͏͏͏͏͏͏͏͏͏͏͏͏͏͏͏͏͏͏͏͏͏͏͏͏͏͏͏͏͏͏͏͏͏͏͏͏͏͏͏͏͏͏͏͏͏͏͏͏͏͏͏͏͏͏͏͏͏͏͏͏͏͏͏͏͏͏͏͏͏͏͏͏͏͏͏͏͏͏͏͏͏͏͏͏͏͏͏͏͏͏͏͏͏͏͏͏͏͏͏͏͏͏͏͏͏͏͏͏͏͏͏͏͏͏͏͏͏͏͏͏͏͏͏͏͏͏͏͏͏͏͏͏͏͏͏͏͏͏͏͏͏͏͏͏͏͏͏͏͏͏͏͏͏͏͏͏͏͏͏͏͏͏͏͏͏͏͏͏͏͏͏͏͏͏͏͏͏͏͏͏͏͏͏͏͏͏͏͏͏͏͏͏͏͏͏͏͏͏͏͏͏͏͏͏͏͏͏͏͏͏͏͏͏͏͏͏͏͏͏͏͏͏͏͏͏͏͏͏͏͏͏͏͏͏͏͏͏͏͏͏͏͏͏͏͏͏͏͏͏͏͏͏͏͏͏͏͏͏͏͏͏͏͏͏͏͏͏͏͏͏͏͏͏͏͏͏͏͏͏͏͏͏͏͏͏͏͏͏͏͏͏͏͏͏͏͏͏͏͏͏͏͏͏͏͏͏͏͏͏͏͏͏͏͏͏͏͏͏͏͏͏͏͏͏͏͏͏͏͏͏͏͏͏͏͏͏͏͏͏͏͏͏͏͏͏͏͏͏͏͏͏͏͏͏͏͏͏͏͏͏͏͏͏͏͏͏͏͏͏͏͏͏͏͏͏͏͏͏͏͏͏͏͏͏͏͏͏͏͏͏͏͏͏͏͏͏͏͏͏͏͏͏͏͏͏͏͏͏͏͏͏͏͏͏͏͏͏͏͏͏͏͏͏͏͏͏͏͏͏͏͏͏͏͏͏͏͏͏͏͏͏͏͏͏͏͏͏͏͏͏͏͏͏͏͏͏͏͏͏͏͏͏͏͏͏͏͏͏͏͏͏͏͏͏͏͏͏͏͏͏͏͏͏͏͏͏͏͏͏͏͏͏͏͏͏͏͏͏͏͏͏͏͏͏͏͏͏͏͏͏͏͏͏͏͏͏͏͏͏͏͏͏͏͏͏͏͏͏͏͏͏͏͏͏͏͏͏͏͏͏͏͏͏͏͏͏͏͏͏͏͏͏͏͏͏͏͏͏͏͏͏͏͏͏͏͏͏͏͏͏͏͏͏͏͏͏͏͏͏͏͏͏͏͏͏͏͏͏͏͏͏͏͏͏͏͏͏͏͏͏͏͏͏͏͏͏͏͏͏͏͏͏͏͏͏͏͏͏͏͏͏͏͏͏͏͏͏͏͏͏͏͏͏͏͏͏͏͏͏͏͏͏͏͏͏͏͏͏͏͏͏͏͏͏͏͏͏͏͏͏͏͏͏͏͏͏͏͏͏͏͏͏͏͏͏͏͏͏͏͏͏͏͏͏͏͏͏͏͏͏͏͏͏͏͏͏͏͏͏͏͏͏͏͏͏͏͏͏͏͏͏͏͏͏͏͏͏͏͏͏͏͏͏͏͏͏͏͏͏͏͏͏͏͏͏͏͏͏͏͏͏͏͏͏͏͏͏͏͏͏͏͏͏͏͏͏͏͏͏͏͏͏͏͏͏͏͏͏͏͏͏͏͏͏͏͏͏͏͏͏͏͏͏͏͏͏͏͏͏͏͏͏͏͏͏͏͏͏͏͏͏͏͏͏͏͏͏͏͏͏͏͏͏͏͏͏͏͏͏͏͏͏͏͏͏͏͏͏͏͏͏͏͏͏͏͏͏͏͏͏͏͏͏͏͏͏͏͏͏͏͏͏͏͏͏͏͏͏͏͏͏͏͏͏͏͏͏͏͏͏͏͏͏͏͏͏͏͏͏͏͏͏͏͏͏͏͏͏͏͏͏͏͏͏͏͏͏͏͏͏͏͏͏͏͏͏͏͏͏͏͏͏͏͏͏͏͏͏͏͏͏͏͏͏͏͏͏͏͏͏͏͏͏͏͏͏͏͏͏͏͏͏͏͏͏͏͏͏͏͏͏͏͏͏͏͏͏͏͏͏͏͏͏͏͏͏͏͏͏͏͏͏͏͏͏͏͏͏͏͏͏͏͏͏͏͏͏͏͏͏͏͏͏͏͏͏͏͏͏͏͏͏͏͏͏͏͏͏͏͏͏͏͏͏͏͏͏͏͏͏͏͏͏͏͏͏͏͏͏͏͏͏͏͏͏͏͏͏͏͏͏͏͏͏͏͏͏͏͏͏͏͏͏͏͏͏͏͏͏͏͏͏͏͏͏͏͏͏͏͏͏͏͏͏͏͏͏͏͏͏͏͏͏͏͏͏͏͏͏͏͏͏͏͏͏͏͏͏͏͏͏͏͏͏͏͏͏͏͏͏͏͏͏͏͏͏͏͏͏͏͏͏͏͏͏͏͏͏͏͏͏͏͏͏͏͏͏͏͏͏͏͏͏͏͏͏͏͏͏͏͏͏͏͏͏͏͏͏͏͏͏͏͏͏͏͏͏͏͏͏͏͏͏͏͏͏͏͏͏͏͏͏͏͏͏͏͏͏͏͏͏͏͏͏͏͏͏͏͏͏͏͏͏͏͏͏͏͏͏͏͏͏͏͏͏͏͏͏͏͏͏͏͏͏͏͏͏͏͏͏͏͏͏͏͏͏͏͏͏͏͏͏͏͏͏͏͏͏͏͏͏͏͏͏͏͏͏͏͏͏͏͏͏͏͏͏͏͏͏͏͏͏͏͏͏͏͏͏͏͏͏͏͏͏͏͏͏͏͏͏͏͏͏͏͏͏͏͏͏͏͏͏͏͏͏͏͏͏͏͏͏͏͏͏͏͏͏͏͏͏͏͏͏͏͏͏͏͏͏͏͏͏͏͏͏͏͏͏͏͏͏͏͏͏͏͏͏͏͏͏͏͏͏͏͏͏͏͏͏͏͏͏͏͏͏͏͏͏͏͏͏͏͏͏͏͏͏͏͏͏͏͏͏͏͏͏͏͏͏͏͏͏͏͏͏͏͏͏͏͏͏͏͏͏͏͏͏͏͏͏͏͏͏͏͏͏͏͏͏͏͏͏͏͏͏͏͏͏͏͏͏͏͏͏͏͏͏͏͏͏͏͏͏͏͏͏͏͏͏͏͏͏͏͏͏͏͏͏͏͏͏͏͏͏͏͏͏͏͏͏͏͏͏͏͏͏͏͏͏͏͏͏͏͏͏͏͏͏͏͏͏͏͏͏͏͏͏͏͏͏͏͏͏͏͏͏͏͏͏͏͏͏͏͏͏͏͏͏͏͏͏͏͏͏͏͏͏͏͏͏͏͏͏͏͏͏͏͏͏͏͏͏͏͏͏͏͏͏͏͏͏͏͏͏͏͏͏͏͏͏͏͏͏͏͏͏͏͏͏͏͏͏͏͏͏͏͏͏͏͏͏͏͏͏͏͏͏͏͏͏͏͏͏͏͏͏͏͏͏͏͏͏͏͏͏͏͏͏͏͏͏͏͏͏͏͏͏͏͏͏͏͏͏͏͏͏͏͏͏͏͏͏͏͏͏͏͏͏͏͏͏͏͏͏͏͏͏͏͏͏͏͏͏͏͏͏͏͏͏͏͏͏͏͏͏͏͏͏͏͏͏͏͏͏͏͏͏͏͏͏͏͏͏͏͏͏͏͏͏͏͏͏͏͏͏͏͏͏͏͏͏͏͏͏͏͏͏͏͏͏͏͏͏͏͏͏͏͏͏͏͏͏͏͏͏͏͏͏͏͏͏͏͏͏͏͏͏͏͏͏͏͏͏͏͏͏͏͏͏͏͏͏͏͏͏͏͏͏͏͏͏͏͏͏͏͏͏͏͏͏͏͏͏͏͏͏͏͏͏͏͏͏͏͏͏͏͏͏͏͏͏͏͏͏͏͏͏͏͏͏͏͏͏͏͏͏͏͏͏͏͏͏͏͏͏͏͏͏͏͏͏͏͏͏͏͏͏͏͏͏͏͏͏͏͏͏͏͏͏͏͏͏͏͏͏͏͏͏͏͏͏͏͏͏͏͏͏͏͏͏͏͏͏͏͏͏͏͏͏͏͏͏͏͏͏͏͏͏͏͏͏͏͏͏͏͏͏͏͏͏͏͏͏͏͏͏͏͏͏͏͏͏͏͏͏͏͏͏͏͏͏͏͏͏͏͏͏͏͏͏͏͏͏͏͏͏͏͏͏͏͏͏͏͏͏͏͏͏͏͏͏͏͏͏͏͏͏͏͏͏͏͏͏͏͏͏͏͏͏͏͏͏͏͏͏͏͏͏͏͏͏͏͏͏͏͏͏͏͏͏͏͏͏͏͏͏͏͏͏͏͏͏͏͏͏͏͏͏͏͏͏͏͏͏͏͏͏͏͏͏͏͏͏͏͏͏͏͏͏͏͏͏͏͏͏͏͏͏͏͏͏͏͏͏͏͏͏͏͏͏͏͏͏͏͏͏͏͏͏͏͏͏͏͏͏͏͏͏͏͏͏͏͏͏͏͏͏͏͏͏͏͏͏͏͏͏͏͏͏͏͏͏͏͏͏͏͏͏͏͏͏͏͏͏͏͏͏͏͏͏͏͏͏͏͏͏͏͏͏͏͏͏͏͏͏͏͏͏͏͏͏͏͏͏͏͏͏͏͏͏͏͏͏͏͏͏͏͏͏͏͏͏͏͏͏͏͏͏͏͏͏͏͏͏͏͏͏͏͏͏͏͏͏͏͏͏͏͏͏͏͏͏͏͏͏͏͏͏͏͏͏͏͏͏͏͏͏͏͏͏͏͏͏͏͏͏͏͏͏͏͏͏͏͏͏͏͏͏͏͏͏͏͏͏͏͏͏͏͏͏͏͏͏͏͏͏͏͏͏͏͏͏͏͏͏͏͏͏͏͏͏͏͏͏͏͏͏͏͏͏͏͏͏͏͏͏͏͏͏͏͏͏͏͏͏͏͏͏͏͏͏͏͏͏͏͏͏͏͏͏͏͏͏͏͏͏͏͏͏͏͏͏͏͏͏͏͏͏͏͏͏͏͏͏͏͏͏͏͏͏͏͏͏͏͏͏͏͏͏͏͏͏͏͏͏͏͏͏͏͏͏͏͏͏͏͏͏͏͏͏͏͏͏͏͏͏͏͏͏͏͏͏͏͏͏͏͏͏͏͏͏͏͏͏͏͏͏͏͏͏͏͏͏͏͏͏͏͏͏͏͏͏͏͏͏͏͏͏͏͏͏͏͏͏͏͏͏͏͏͏͏͏͏͏͏͏͏͏͏͏͏͏͏͏͏͏͏͏͏͏͏͏͏͏͏͏͏͏͏͏͏͏͏͏͏͏͏͏͏͏͏͏͏͏͏͏͏͏͏͏͏͏͏͏͏͏͏͏͏͏͏͏͏͏͏5 Hari = 38.000\n7 Hari = 52.000\n10 Hari = 71.000\n14 Hari = 100.000\n20 Hari = 123.000\n30 Hari = 172.500\n60 Hari = 329.000\n90 Hari  = 475.500",
      "isImage": false,
      "image_url": "-"
   },
   {
      "id": "120363041567830603@g.us",
      "key": "EVENT",
      "response": "( *TERGANTUNG ADMIN* )",
      "isImage": false,
      "image_url": "-"
   },
   {
      "id": "120363041321406709@g.us",
      "key": "judul",
      "response": "isi text",
      "isImage": false,
      "image_url": "-"
   },
   {
      "id": "120363041321406709@g.us",
      "key": "Epep",
      "response": "Li",
      "isImage": false,
      "image_url": "-"
   }
]